[
	{ "s": "ФАЙЛ", "p": [19, 16] },
	{ "s": "ФАЙЛЕ", "p": [16, 13, 12] },
	{ "s": "ФАЙЛОМ", "p": [19, 16] },
	{ "s": "ФАЙЛЫ", "p": [23, 19, 16] },
	{ "s": "ФАКТ", "p": [32] },
	{ "s": "ФАКТА", "p": [32, 28] },
	{ "s": "ФАКТИЧЕСКИЕ", "p": [32] },
	{ "s": "ФАКТИЧЕСКИХ", "p": [32] },
	{ "s": "ФАКТИЧЕСКОЕ", "p": [32] },
	{ "s": "ФАКТИЧЕСКОМ", "p": [32] },
	{ "s": "ФАКТНЫЙ", "p": [26] },
	{ "s": "ФАКТУ", "p": [25] },
	{ "s": "ФИКСИРУЕТСЯ", "p": [25] },
	{ "s": "ФИН", "p": [13] },
	{ "s": "ФИНАНСОВЫЙ", "p": [13] },
	{ "s": "ФИНАНСОВЫХ", "p": [13] },
	{ "s": "ФИО", "p": [32] },
	{ "s": "ФОРМ", "p": [25] },
	{ "s": "ФОРМА", "p": [33, 21] },
	{ "s": "ФОРМАХ", "p": [3] },
	{ "s": "ФОРМЕ", "p": [32, 30] },
	{ "s": "ФОРМИРОВАНИЕ", "p": [25, 32, 28, 26, 13, 5] },
	{ "s": "ФОРМИРОВАНИЕМ", "p": [32] },
	{ "s": "ФОРМИРОВАНИИ", "p": [30] },
	{ "s": "ФОРМИРОВАНИЮ", "p": [20] },
	{ "s": "ФОРМИРОВАНИЯ", "p": [25, 28, 32] },
	{ "s": "ФОРМИРОВАТЬСЯ", "p": [32] },
	{ "s": "ФОРМИРУЕТСЯ", "p": [25, 32] },
	{ "s": "ФОРМИРУЮТСЯ", "p": [32, 25] },
	{ "s": "ФОРМУ", "p": [3] },
	{ "s": "ФОРМЫ", "p": [32, 25] },
	{ "s": "ФУНКЦИЙ", "p": [32, 23, 30] },
	{ "s": "ФУНКЦИОНАЛ", "p": [25] },
	{ "s": "ФУНКЦИОНАЛА", "p": [25] },
	{ "s": "ФУНКЦИОНАЛЬНОСТИ", "p": [26, 32, 25, 16, 5] },
	{ "s": "ФУНКЦИОНАЛЬНЫЕ", "p": [12, 11] },
	{ "s": "ФУНКЦИОНИРОВАНИИ", "p": [30] },
	{ "s": "ФУНКЦИОНИРОВАНИЯ", "p": [30] }
]