[
	{ "s": "О", "p": [20, 13, 16] },
	{ "s": "ОБ", "p": [20] },
	{ "s": "ОБМЕН", "p": [13] },
	{ "s": "ОБОЗНАЧЕНИЕ", "p": [20] },
	{ "s": "ОБОСНОВАННЫХ", "p": [13] },
	{ "s": "ОБРАБОТКИ", "p": [12, 18, 11] },
	{ "s": "ОБРАБОТКОЙ", "p": [20, 16] },
	{ "s": "ОБРАЩЕНИЕ", "p": [20] },
	{ "s": "ОБРАЩЕНИЕМ", "p": [20] },
	{ "s": "ОБРАЩЕНИЙ", "p": [20, 16] },
	{ "s": "ОБРАЩЕНИЮ", "p": [20, 16] },
	{ "s": "ОБРАЩЕНИЯ", "p": [20] },
	{ "s": "ОБРАЩЕНИЯМ", "p": [20] },
	{ "s": "ОБРАЩЕНИЯМИ", "p": [20, 18] },
	{ "s": "ОБЪЕКТАХ", "p": [16] },
	{ "s": "ОБЪЕМ", "p": [14, 20] },
	{ "s": "ОБЪЕМА", "p": [18] },
	{ "s": "ОБЪЕМОМ", "p": [4] },
	{ "s": "ОБЪЕМУ", "p": [20] },
	{ "s": "ОГЛАВЛЕНИЕ", "p": [16] },
	{ "s": "ОГРАНИЧЕНИЯ", "p": [16] },
	{ "s": "ОГРАНИЧЕННОЕ", "p": [18] },
	{ "s": "ОДИН", "p": [20, 13] },
	{ "s": "ОДНАКО", "p": [20] },
	{ "s": "ОДНИМ", "p": [20] },
	{ "s": "ОДНОЙ", "p": [20] },
	{ "s": "ОДНОМ", "p": [20] },
	{ "s": "ОЗНАКОМИТЕЛЬНЫХ", "p": [16] },
	{ "s": "ОЗНАКОМЛЕНИЯ", "p": [13] },
	{ "s": "ОКОНЧАНИЮ", "p": [20] },
	{ "s": "ОКОНЧАНИЯ", "p": [20, 13] },
	{ "s": "ОНЛАЙН", "p": [10] },
	{ "s": "ООО", "p": [16] },
	{ "s": "ОПЕРАТИВНОГО", "p": [18] },
	{ "s": "ОПЕРАТИВНОЕ", "p": [20] },
	{ "s": "ОПЕРАЦИИ", "p": [11] },
	{ "s": "ОПЕРАЦИЙ", "p": [11, 9] },
	{ "s": "ОПЕРАЦИОННАЯ", "p": [20] },
	{ "s": "ОПЕРАЦИОННОГО", "p": [20] },
	{ "s": "ОПЕРАЦИОННОЙ", "p": [20] },
	{ "s": "ОПЕРАЦИОННОМУ", "p": [20] },
	{ "s": "ОПЕРАЦИОННЫЙ", "p": [20] },
	{ "s": "ОПЕРАЦИОННЫХ", "p": [20] },
	{ "s": "ОПЕРАЦИЮ", "p": [10, 11] },
	{ "s": "ОПИСАН", "p": [20, 16] },
	{ "s": "ОПИСАНИЕ", "p": [11, 20, 12, 25] },
	{ "s": "ОПИСАНИЕМ", "p": [13] },
	{ "s": "ОПИСАНИИ", "p": [11] },
	{ "s": "ОПИСАНИЯ", "p": [18, 16] },
	{ "s": "ОПИСЫВАЮЩИЙ", "p": [13] },
	{ "s": "ОПОВЕЩЕН", "p": [13] },
	{ "s": "ОПОВЕЩЕНИЕ", "p": [13] },
	{ "s": "ОПОВЕЩЕНИЯ", "p": [13] },
	{ "s": "ОПОЗДАНИЯ", "p": [13] },
	{ "s": "ОПРЕДЕЛЕН", "p": [20, 13] },
	{ "s": "ОПРЕДЕЛЕНА", "p": [13] },
	{ "s": "ОПРЕДЕЛЕНИЕ", "p": [13] },
	{ "s": "ОПРЕДЕЛЕНИЯ", "p": [17, 16] },
	{ "s": "ОПРЕДЕЛЕННЫЕ", "p": [20] },
	{ "s": "ОПРЕДЕЛЕНЫ", "p": [13] },
	{ "s": "ОПРЕДЕЛИТЬ", "p": [20] },
	{ "s": "ОПРЕДЕЛЯЕТСЯ", "p": [13] },
	{ "s": "ОПРЕДЕЛЯЮТСЯ", "p": [13] },
	{ "s": "ОРГАНИЗАЦИИ", "p": [18] },
	{ "s": "ОРГАНИЗАЦИОННО", "p": [18] },
	{ "s": "ОРГАНИЗАЦИОННО-ТЕХНОЛОГИЧЕСКИХ", "p": [18] },
	{ "s": "ОРГАНИЗАЦИЯ", "p": [20] },
	{ "s": "ОРИЕНТИРОВОЧНОЙ", "p": [13] },
	{ "s": "ОСВОЕНИЮ", "p": [25] },
	{ "s": "ОСНОВАНИИ", "p": [20, 13, 5, 3, 2] },
	{ "s": "ОСНОВАНИЯ", "p": [3] },
	{ "s": "ОСНОВЕ", "p": [18] },
	{ "s": "ОСНОВНОЕ", "p": [20] },
	{ "s": "ОСНОВНЫЕ", "p": [20, 18, 11] },
	{ "s": "ОСТАЛЬНЫХ", "p": [20] },
	{ "s": "ОСУЩЕСТВЛЯЕМЫЕ", "p": [20] },
	{ "s": "ОСУЩЕСТВЛЯЕТСЯ", "p": [20] },
	{ "s": "ОТ", "p": [20, 16, 13] },
	{ "s": "ОТВ", "p": [13] },
	{ "s": "ОТВЕТ", "p": [20] },
	{ "s": "ОТВЕТСТВЕННОГО", "p": [13] },
	{ "s": "ОТВЕТСТВЕННОЕ", "p": [20] },
	{ "s": "ОТВЕТСТВЕННОМ", "p": [13] },
	{ "s": "ОТВЕТСТВЕННОМУ", "p": [13] },
	{ "s": "ОТВЕТСТВЕННЫЕ", "p": [16] },
	{ "s": "ОТВЕТСТВЕННЫЙ", "p": [13, 20, 14] },
	{ "s": "ОТВЕТСТВЕННЫМ", "p": [13] },
	{ "s": "ОТВЕТСТВЕННЫХ", "p": [16] },
	{ "s": "ОТГРУЗИТЬ", "p": [13] },
	{ "s": "ОТГРУЗКИ", "p": [5, 4] },
	{ "s": "ОТДЕЛЬНО", "p": [20] },
	{ "s": "ОТДЕЛЬНОЙ", "p": [20] },
	{ "s": "ОТДЕЛЬНЫЙ", "p": [20] },
	{ "s": "ОТДЕЛЬНЫХ", "p": [20, 16] },
	{ "s": "ОТКРЫВАЕМОЙ", "p": [20] },
	{ "s": "ОТЛИЧАТЬСЯ", "p": [16] },
	{ "s": "ОТНЕСТИ", "p": [20] },
	{ "s": "ОТОБРАЖАЮТСЯ", "p": [20] },
	{ "s": "ОТПРАВИТЬ", "p": [13] },
	{ "s": "ОТПРАВКА", "p": [13] },
	{ "s": "ОТПРАВКИ", "p": [14, 13] },
	{ "s": "ОТПРАВЛЕНО", "p": [13] },
	{ "s": "ОТРАБОТАННОГО", "p": [14] },
	{ "s": "ОТРАБОТАННОЕ", "p": [14] },
	{ "s": "ОТРАБОТАННОМУ", "p": [20, 16] },
	{ "s": "ОТРАЖАЕМЫМ", "p": [16] },
	{ "s": "ОТРАЖАЕТСЯ", "p": [13] },
	{ "s": "ОТРАЖАЮТСЯ", "p": [20] },
	{ "s": "ОТРАЖЕН", "p": [20, 13] },
	{ "s": "ОТРАЖЕНА", "p": [20] },
	{ "s": "ОТРАЖЕНИЕ", "p": [20, 16, 14, 13] },
	{ "s": "ОТРАЖЕНИИ", "p": [20, 18, 16] },
	{ "s": "ОТРАЖЕНИЮ", "p": [9, 20, 13] },
	{ "s": "ОТРАЖЕНИЯ", "p": [20, 18, 16] },
	{ "s": "ОТРАЖЕНО", "p": [20, 14] },
	{ "s": "ОТРАЖЕНЫ", "p": [13] },
	{ "s": "ОТРАЗИТЬ", "p": [20, 10, 13] },
	{ "s": "ОТСУТСТВИЕ", "p": [20] },
	{ "s": "ОТСУТСТВИИ", "p": [20] },
	{ "s": "ОТСУТСТВУЕТ", "p": [8] },
	{ "s": "ОТЧЕТ", "p": [14, 3] },
	{ "s": "ОТЧЕТ/ФОРМУ", "p": [3] },
	{ "s": "ОТЧЕТА", "p": [6] },
	{ "s": "ОТЧЕТАХ", "p": [3] },
	{ "s": "ОТЧЕТАХ/ФОРМАХ", "p": [3] },
	{ "s": "ОТЧЕТНОСТИ", "p": [14] },
	{ "s": "ОТЧЕТНОСТЬ", "p": [14] },
	{ "s": "ОТЧЕТОВ", "p": [20] },
	{ "s": "ОТЧЕТОМ", "p": [6] },
	{ "s": "ОТЧЕТЫ", "p": [14, 6] },
	{ "s": "ОФИСА", "p": [14] },
	{ "s": "ОФОРМЛЕНИЕ", "p": [20] },
	{ "s": "ОФОРМЛЯТЬ", "p": [20] },
	{ "s": "ОЦЕНКА", "p": [8, 13] },
	{ "s": "ОЦЕНКЕ", "p": [20] },
	{ "s": "ОЦЕНКИ", "p": [13] },
	{ "s": "ОШИБКИ", "p": [20, 16, 13] }
]