[
	{ "s": "БАЗА", "p": [19, 21] },
	{ "s": "БАЗЕ", "p": [20] },
	{ "s": "БЕЗ", "p": [14, 20, 18, 8, 5] },
	{ "s": "БИБЛИОТЕК", "p": [18] },
	{ "s": "БИТ", "p": [8] },
	{ "s": "БИТ_УПРАВЛЕНИЕ", "p": [20] },
	{ "s": "БЛИЖЕ", "p": [20] },
	{ "s": "БЛОКАМ", "p": [16] },
	{ "s": "БОЛЕЗНИ", "p": [20] },
	{ "s": "БП", "p": [14, 13, 12] },
	{ "s": "БУДЕТ", "p": [20] },
	{ "s": "БУДУТ", "p": [20] },
	{ "s": "БЫЛ", "p": [20] },
	{ "s": "БЫЛИ", "p": [20] },
	{ "s": "БЫЛО", "p": [20] },
	{ "s": "БЫТЬ", "p": [20, 13, 18] },
	{ "s": "БЮДЖЕТ", "p": [13] },
	{ "s": "БЮДЖЕТА", "p": [7, 8, 13] },
	{ "s": "БЮДЖЕТИРОВАНИЕ", "p": [20] },
	{ "s": "БЮДЖЕТУ", "p": [14, 8] }
]