[
	{ "s": "НА", "p": [32, 25, 16, 19, 28, 30, 26, 24, 13, 23, 7, 4, 5, 3, 27, 21, 18, 17, 15, 12, 11, 2] },
	{ "s": "НАГРУЗОЧНОГО", "p": [25] },
	{ "s": "НАД", "p": [32] },
	{ "s": "НАДО", "p": [25] },
	{ "s": "НАЗВАНИЕ", "p": [19] },
	{ "s": "НАЗНАЧЕН", "p": [25, 16] },
	{ "s": "НАЗНАЧЕНИЕ", "p": [25] },
	{ "s": "НАЗНАЧЕНИИ", "p": [25] },
	{ "s": "НАЗНАЧЕНИЯ", "p": [25] },
	{ "s": "НАЗНАЧЕННОМ", "p": [25] },
	{ "s": "НАИМЕНОВАНИЕ", "p": [32, 19, 16, 13, 23, 12] },
	{ "s": "НАИМЕНОВАНИЕМ", "p": [32] },
	{ "s": "НАИМЕНОВАНИИ", "p": [32] },
	{ "s": "НАИМЕНОВАНИЯ", "p": [30, 25, 19] },
	{ "s": "НАЙДЕНА", "p": [25] },
	{ "s": "НАЙДЕНЫ", "p": [25] },
	{ "s": "НАЛИЧИИ", "p": [16, 19, 26] },
	{ "s": "НАЛОГАМ", "p": [13] },
	{ "s": "НАЛОГИ", "p": [13] },
	{ "s": "НАЛОГОВ", "p": [13] },
	{ "s": "НАЛОГОВОМУ", "p": [13] },
	{ "s": "НАЛОГОВЫЙ", "p": [13] },
	{ "s": "НАЛОГУ", "p": [13] },
	{ "s": "НАПРАВЛЕННОЕ", "p": [30] },
	{ "s": "НАПРАВЛЕННЫЙ", "p": [30] },
	{ "s": "НАПРИМЕР", "p": [32, 30] },
	{ "s": "НАСТРОЕК", "p": [32] },
	{ "s": "НАСТРОЙКИ", "p": [32] },
	{ "s": "НАХОДИТСЯ", "p": [19, 16] },
	{ "s": "НАХОДИТЬСЯ", "p": [32] },
	{ "s": "НАЧАЛА", "p": [32, 25] },
	{ "s": "НАЧАЛЕ", "p": [32] },
	{ "s": "НАЧАЛУ", "p": [32] },
	{ "s": "НАЧАЛЬНАЯ", "p": [1] },
	{ "s": "НАЧАТ", "p": [25] },
	{ "s": "НАЧАТА", "p": [19, 16] },
	{ "s": "НАЧАТЫ", "p": [25, 16, 19] },
	{ "s": "НАЧАТЬ", "p": [32] },
	{ "s": "НАЧИНАЯ", "p": [32] },
	{ "s": "НАЧИСЛЕНИЙ", "p": [13] },
	{ "s": "НЕ", "p": [25, 32, 17, 28, 26, 19, 16, 37, 36, 35, 30, 27, 24, 23, 18, 15, 11] },
	{ "s": "НЕАКТУАЛЬНЫМИ", "p": [25] },
	{ "s": "НЕВЫХОДОВ", "p": [32] },
	{ "s": "НЕДОСТАТОЧНО", "p": [25] },
	{ "s": "НЕДОСТАЮЩУЮ", "p": [25] },
	{ "s": "НЕЗАПЛАНИРОВАННЫХ", "p": [32] },
	{ "s": "НЕЗНАЧИТЕЛЬНАЯ", "p": [32] },
	{ "s": "НЕКОТОРОЕ", "p": [32] },
	{ "s": "НЕОБХОДИМА", "p": [30] },
	{ "s": "НЕОБХОДИМО", "p": [32, 19, 16, 3] },
	{ "s": "НЕОБХОДИМОЙ", "p": [32, 28] },
	{ "s": "НЕОБХОДИМОМУ", "p": [32] },
	{ "s": "НЕОБХОДИМОСТИ", "p": [32, 28, 25] },
	{ "s": "НЕОБХОДИМОСТЬ", "p": [25, 32] },
	{ "s": "НЕОБХОДИМОСТЬЮ", "p": [32] },
	{ "s": "НЕОБХОДИМЫЕ", "p": [32, 25] },
	{ "s": "НЕОБХОДИМЫМ", "p": [32] },
	{ "s": "НЕОБХОДИМЫХ", "p": [32, 23] },
	{ "s": "НЕОПЕРАЦИОННОЙ", "p": [32] },
	{ "s": "НЕОПЕРАЦИОННЫЕ", "p": [32] },
	{ "s": "НЕПОСРЕДСТВЕННО", "p": [32, 28] },
	{ "s": "НЕПОСРЕДСТВЕННЫХ", "p": [30] },
	{ "s": "НЕРАСПЛАНИРОВАННЫМИ", "p": [25] },
	{ "s": "НЕРАСПЛАНИРОВАННЫМИ/НЕАКТУАЛЬНЫМИ", "p": [25] },
	{ "s": "НЕСКОЛЬКИХ", "p": [32] },
	{ "s": "НЕСКОЛЬКО", "p": [32, 19] },
	{ "s": "НЕТ", "p": [32] },
	{ "s": "НЗП", "p": [13] },
	{ "s": "НИЖЕ", "p": [25] },
	{ "s": "НИЗКАЯ", "p": [32] },
	{ "s": "НИЗКОЙ", "p": [32] },
	{ "s": "НО", "p": [32, 12] },
	{ "s": "НОВАЯ", "p": [25] },
	{ "s": "НОВОГО", "p": [32] },
	{ "s": "НОВОЙ", "p": [20, 25, 32] },
	{ "s": "НОВОМ", "p": [32] },
	{ "s": "НОВУЮ", "p": [32] },
	{ "s": "НОВЫЕ", "p": [32] },
	{ "s": "НОВЫЙ", "p": [32, 25] },
	{ "s": "НОВЫХ", "p": [32, 30] },
	{ "s": "НОМЕНКЛАТУРА", "p": [32, 25] },
	{ "s": "НОМЕНКЛАТУРУ", "p": [32, 25] },
	{ "s": "НОМЕНКЛАТУРЫ", "p": [32, 25] },
	{ "s": "НОМЕР", "p": [32, 19, 16] },
	{ "s": "НОМЕРЕ", "p": [19] },
	{ "s": "НОРМАТИВНО", "p": [31, 30] },
	{ "s": "НОРМАТИВНО-СПРАВОЧНАЯ", "p": [31, 30] },
	{ "s": "НОРМАТИВНЫЕ", "p": [28] },
	{ "s": "НОСИТЕЛЯХ", "p": [23] },
	{ "s": "НОСЯТ", "p": [28] },
	{ "s": "НСИ", "p": [32, 25, 30, 28, 12, 31, 13] },
	{ "s": "НСИ)/МАСТЕР-ДАННЫЕ/ОСНОВНЫЕ", "p": [30] },
	{ "s": "НУЖНЫЙ", "p": [21] },
	{ "s": "НУЛЕВОГО", "p": [16] },
	{ "s": "НУЛЕВЫМ", "p": [16] }
]