{
	"1": ["Начальная страница", "index.htm"],
	"2": ["1. Вопросы по аналитике ERP АСУП", "voprosy_po_analitike_erp_asup.htm"],
	"3": ["1.1. Статьи бюджета", "stati_byudzheta.htm"],
	"4": ["1.1.1. Как указать статью бюджета в заказе клиента?", "kak_ukazat_statyu_byudzheta_v_zakaze_klienta_.htm"],
	"5": ["1.2. Функциональные блоки и разделы учета", "funktsionalnye_bloki_i_razdely_ucheta.htm"],
	"6": ["АСУП Функциональные блоки: Состав", "asup_funktsionalnye_bloki__sostav.htm"],
	"7": ["АСУП Разделы учета: Состав", "asup_razdely_ucheta__sostav.htm"],
	"8": ["ERP: Функциональные блоки", "erp__funktsionalnye_bloki.htm"],
	"9": ["ERP: Разделы учета", "erp__razdely_ucheta.htm"],
	"10": ["Отчеты", "otchety.htm"],
	"11": ["Каким отчетом проверить количество и качество сделок на разработку?", "kakim_otchetom_proverit_kolichestvo_i_kachestvo_sdelok_na_razrabotku_.htm"],
	"12": ["Как сформировать отчет по заказам клиентов в разрезе видов сделок Сопровождение/Разработка?", "kak_sformirovat_otchet_po_zakazam_klientov_v_razreze_vidov_sdelok_soprovozhdenie_razrabotka_.htm"],
	"13": ["Ввод данных по сопровождению", "vvod_dannykh_po_soprovozhdeniyu.htm"],
	"14": ["Ввод данных по разработке", "vvod_dannykh_po_razrabotke.htm"],
	"15": ["Как посмотреть исполнение заказов клиентов?", "kak_posmotret_ispolnenie_zakazov_klientov_.htm"],
	"16": ["Как посмотреть график отпусков команды?", "kak_posmotret_grafik_otpuskov_komandy_.htm"],
	"17": ["2. Вопросы по отражению операций", "voprosy_po_otrazheniyu_operatsij.htm"],
	"18": ["2.1. Как отразить состояние обработки Заявки?", "kak_otrazit_sostoyanie_obrabotki_zayavki_.htm"],
	"19": ["2.1.1. ДО: отражение состояния обработки Заявки", "do__otrazhenie_sostoyaniya_obrabotki_zayavki.htm"],
	"20": ["2.1.2. ERP: отражение состояния обработки Заявки", "erp__otrazhenie_sostoyaniya_obrabotki_zayavki.htm"],
	"21": ["2.2. Как отразить состояние обработки ЭО?", "kak_otrazit_sostoyanie_obrabotki_eho_.htm"],
	"22": ["2.2.1. ДО: отражение состояния обработки ЭО", "do__otrazhenie_sostoyaniya_obrabotki_eho.htm"],
	"23": ["2.3. Как отразить операцию в новой системе?", "kak_otrazit_operatsiyu_v_novoj_sisteme_.htm"],
	"24": ["2.4. Как связать объект ERP с документом ДО?", "kak_svyazat_obekt_erp_s_dokumentom_do_.htm"],
	"25": ["2.5. Как отменить связь объекта ERP с документом ДО?", "kak_otmenit_svyaz_obekta_erp_s_dokumentom_do_.htm"],
	"26": ["2.6. Как запланировать отпуск?", "kak_zaplanirovat_otpusk_.htm"],
	"27": ["2.7. Не заполнена доступность ВРЦ на планируемый период, что делать?", "ne_zapolnena_dostupnost_vrts_na_planiruemyj_period__chto_delat_.htm"],
	"28": ["Заполнить Производственный календрь", "zapolnit_proizvodstvennyj_kalendr.htm"],
	"29": ["Заполнить График работы предприятия", "zapolnit_grafik_raboty_predpriyatiya.htm"],
	"30": ["Заполнить доступность ВРЦ", "zapolnit_dostupnost_vrts.htm"],
	"31": ["2.8. Как запланировать выпуск работ по плану графику ЭО", "kak_zaplanirovat_vypusk_rabot_po_planu_grafiku_eho.htm"],
	"32": ["3. ОПИСАНИЕ ОПЕРАЦИЙ", "opisanie_operatsij.htm"],
	"33": ["3.1. Описание БП обработки Заявок на планируемый период", "opisanie_bp_obrabotki_zayavok_na_planiruemyj_period.htm"],
	"34": ["БП реализации Заявки", "bp_realizatsii_zayavki.htm"],
	"35": ["РЕГУЛЯРНЫЕ ЗАДАЧИ БП", "regulyarnye_zadachi_bp.htm"],
	"36": ["3.2. Инструкции по сопровождению", "instruktsii_po_soprovozhdeniyu.htm"],
	"37": ["Практическое руководство пользователя по планированию и производству текущих работ по Сопровождению", "prakticheskoe_rukovodstvo_polzovatelya_po_planirovaniyu_i_proizvodstvu_tekushchikh_rabot_po_soprovozhdeniyu.htm"],
	"38": ["Термины и определения", "terminy_i_opredeleniya.htm"],
	"39": ["Глоссарий", "glossarij.htm"],
	"40": ["Список сокращений", "spisok_sokrashchenij.htm"],
	"41": ["Планирование работ по Сопровождению в ЕРП", "planirovanie_rabot_po_soprovozhdeniyu_v_erp.htm"],
	"42": ["3.3. Инструкции по разработке", "instruktsii_po_razrabotke.htm"],
	"43": ["3.3.1. Инструкциия по инструменту тестирования прикладных решений «Vanessa behavior»", "instruktsiiya_po_instrumentu_testirovaniya_prikladnykh_reshenij__vanessa_behavior_.htm"],
	"44": ["Оглавление", "oglavlenie_2.htm"],
	"45": ["3.3.1.1. Feature файлы", "feature_fajly.htm"],
	"46": ["3.3.1.2. Создание автотестов", "sozdanie_avtotestov.htm"],
	"47": ["Создание автоматизированных сценариев", "sozdanie_avtomatizirovannykh_stsenariev.htm"],
	"48": ["Наполнение шагов сценариев кодом проверки поведения", "napolnenie_shagov_stsenariev_kodom_proverki_povedeniya.htm"],
	"49": ["3.3.1.3. Запуск выполнения сценариев", "zapusk_vypolneniya_stsenariev.htm"],
	"50": ["3.3.1.4. Требования к разработчикам", "trebovaniya_k_razrabotchikam.htm"],
	"51": ["3.3.1.5. Требования к аналитикам", "trebovaniya_k_analitikam.htm"],
	"52": ["3.3.1.6. Детализация тестов", "detalizatsiya_testov.htm"],
	"53": ["3.3.2. Отражение отработанного времени в ERP", "otrazhenie_otrabotannogo_vremeni_v_erp.htm"],
	"54": ["4. ТЕРМИНЫ И СОКРАЩЕНИЯ", "terminy_i_sokrashcheniya.htm"],
	"55": ["5. ПОДГОТОВКА К РАБОТЕ", "podgotovka_k_rabote.htm"],
	"56": ["5.1. Порядок проверки работоспособности", "poryadok_proverki_rabotosposobnosti.htm"],
	"57": ["5.2. Порядок загрузки данных и программ", "poryadok_zagruzki_dannykh_i_programm.htm"],
	"58": ["6. РЕКОМЕНДАЦИИ ПО ОСВОЕНИЮ", "rekomendatsii_po_osvoeniyu.htm"]
}